cdlpto/__init__.py
cdlpto/_version.py
cdlpto/cli.py
cdlpto/config.py
cdlpto/email.py
cdlpto/pdf.py
cdlpto/pto.py
cdlpto-0.2.1.dist-info/METADATA
cdlpto-0.2.1.dist-info/WHEEL
cdlpto-0.2.1.dist-info/entry_points.txt
cdlpto-0.2.1.dist-info/top_level.txt
cdlpto-0.2.1.dist-info/RECORD
