Metadata-Version: 2.1
Name: cdlpto
Version: 0.2.1
Summary: Fill out the CDL PTO PDF form
Author-email: Tom Baldwin <tkb@sent.com>
Project-URL: source, https://github.com/baldwint/cdlpto
Requires-Dist: appdirs
Requires-Dist: python-dateutil
Requires-Dist: click
Requires-Dist: PyPDF2 (<3)
Requires-Dist: reportlab
Requires-Dist: tomli
